{
  "credit": "Made with Blockbench",
  "texture_size": [
    24,
    24
  ],
  "elements": [
    {
      "from": [
        9.375,
        3,
        5.95
      ],
      "to": [
        9.75,
        3.425,
        12.05
      ],
      "rotation": {
        "angle": 0,
        "axis": "y",
        "origin": [
          8.2,
          3,
          15.5
        ]
      },
      "faces": {
        "north": {
          "uv": [
            12,
            2.66667,
            12.33333,
            2.83333
          ],
          "texture": "#0"
        },
        "east": {
          "uv": [
            11.33333,
            4,
            15.33333,
            4.16667
          ],
          "texture": "#0"
        },
        "south": {
          "uv": [
            12,
            3.33333,
            12.33333,
            3.5
          ],
          "texture": "#0"
        },
        "west": {
          "uv": [
            11.33333,
            4.66667,
            15.33333,
            4.83333
          ],
          "texture": "#0"
        },
        "up": {
          "uv": [
            11,
            8,
            10.66667,
            4
          ],
          "texture": "#0"
        },
        "down": {
          "uv": [
            11,
            8,
            10.66667,
            12
          ],
          "texture": "#0"
        }
      }
    },
    {
      "from": [
        9.7,
        3,
        6
      ],
      "to": [
        13.7,
        3.3,
        12
      ],
      "rotation": {
        "angle": 22.5,
        "axis": "z",
        "origin": [
          9.65,
          3,
          9.425
        ]
      },
      "faces": {
        "north": {
          "uv": [
            0,
            12,
            2.66667,
            12.16667
          ],
          "texture": "#0"
        },
        "east": {
          "uv": [
            11.33333,
            5.33333,
            15.33333,
            5.5
          ],
          "texture": "#0"
        },
        "south": {
          "uv": [
            12,
            0,
            14.66667,
            0.16667
          ],
          "texture": "#0"
        },
        "west": {
          "uv": [
            11.33333,
            6,
            15.33333,
            6.16667
          ],
          "texture": "#0"
        },
        "up": {
          "uv": [
            2.66667,
            8,
            0,
            4
          ],
          "texture": "#0"
        },
        "down": {
          "uv": [
            5.33333,
            4,
            2.66667,
            8
          ],
          "texture": "#0"
        }
      }
    },
    {
      "from": [
        5.275,
        3.65,
        6
      ],
      "to": [
        9.275,
        3.95,
        12
      ],
      "rotation": {
        "angle": -22.5,
        "axis": "z",
        "origin": [
          7.75,
          3,
          9.425
        ]
      },
      "faces": {
        "north": {
          "uv": [
            12,
            0.66667,
            14.66667,
            0.83333
          ],
          "texture": "#0"
        },
        "east": {
          "uv": [
            11.33333,
            6.66667,
            15.33333,
            6.83333
          ],
          "texture": "#0"
        },
        "south": {
          "uv": [
            12,
            1.33333,
            14.66667,
            1.5
          ],
          "texture": "#0"
        },
        "west": {
          "uv": [
            11.33333,
            7.33333,
            15.33333,
            7.5
          ],
          "texture": "#0"
        },
        "up": {
          "uv": [
            8,
            8,
            5.33333,
            4
          ],
          "texture": "#0"
        },
        "down": {
          "uv": [
            9.33333,
            0,
            6.66667,
            4
          ],
          "texture": "#0"
        }
      }
    },
    {
      "from": [
        9.575,
        3.275,
        6.125
      ],
      "to": [
        13.5,
        3.6,
        11.9
      ],
      "rotation": {
        "angle": 22.5,
        "axis": "z",
        "origin": [
          9.65,
          3,
          9.425
        ]
      },
      "faces": {
        "north": {
          "uv": [
            12,
            2,
            14.66667,
            2.16667
          ],
          "texture": "#0"
        },
        "east": {
          "uv": [
            11.33333,
            9.33333,
            15.16667,
            9.5
          ],
          "texture": "#0"
        },
        "south": {
          "uv": [
            2.66667,
            12,
            5.33333,
            12.16667
          ],
          "texture": "#0"
        },
        "west": {
          "uv": [
            11.33333,
            10,
            15.16667,
            10.16667
          ],
          "texture": "#0"
        },
        "up": {
          "uv": [
            2.66667,
            11.83333,
            0,
            8
          ],
          "texture": "#0"
        },
        "down": {
          "uv": [
            5.33333,
            8,
            2.66667,
            11.83333
          ],
          "texture": "#0"
        }
      }
    },
    {
      "from": [
        5.5275,
        3.28401,
        6.125
      ],
      "to": [
        9.7775,
        3.58401,
        11.875
      ],
      "rotation": {
        "angle": -22.5,
        "axis": "z",
        "origin": [
          9.425,
          3,
          9.35
        ]
      },
      "faces": {
        "north": {
          "uv": [
            11.33333,
            10.66667,
            14.16667,
            10.83333
          ],
          "texture": "#0"
        },
        "east": {
          "uv": [
            11.33333,
            8,
            15.16667,
            8.16667
          ],
          "texture": "#0"
        },
        "south": {
          "uv": [
            11.33333,
            11.33333,
            14.16667,
            11.5
          ],
          "texture": "#0"
        },
        "west": {
          "uv": [
            11.33333,
            8.66667,
            15.16667,
            8.83333
          ],
          "texture": "#0"
        },
        "up": {
          "uv": [
            2.83333,
            3.83333,
            0,
            0
          ],
          "texture": "#0"
        },
        "down": {
          "uv": [
            6.16667,
            0,
            3.33333,
            3.83333
          ],
          "texture": "#0"
        }
      }
    }
  ],
  "display": {
    "thirdperson_righthand": {
      "rotation": [
        -79.62,
        -4.85,
        178.01
      ],
      "translation": [
        0,
        1.25,
        5.5
      ]
    },
    "thirdperson_lefthand": {
      "rotation": [
        -79.62,
        -4.85,
        178.01
      ],
      "translation": [
        0,
        1.25,
        5.5
      ]
    },
    "firstperson_righthand": {
      "rotation": [
        -150,
        -4.85,
        178.01
      ],
      "translation": [
        0,
        6.25,
        5.5
      ]
    },
    "firstperson_lefthand": {
      "rotation": [
        -150,
        -4.85,
        178.01
      ],
      "translation": [
        0,
        6.25,
        5.5
      ]
    },
    "ground": {
      "translation": [
        0,
        1.75,
        0
      ]
    },
    "gui": {
      "rotation": [
        82,
        43,
        0
      ],
      "translation": [
        -2.75,
        0,
        0
      ],
      "scale": [
        1.62,
        1.62,
        1.62
      ]
    },
    "fixed": {
      "rotation": [
        89,
        0,
        0
      ],
      "translation": [
        -3.75,
        2.75,
        7
      ],
      "scale": [
        2.22,
        2.22,
        2.22
      ]
    }
  }
}